kripweb/__init__.py
kripweb/asgi.py
kripweb/constant.py
kripweb/error.py
kripweb/handler.py
kripweb/path.py
kripweb/request.py
kripweb/response.py
kripweb/setting.py
kripweb/view.py
kripweb-0.0.4.dist-info/LICENSE
kripweb-0.0.4.dist-info/METADATA
kripweb-0.0.4.dist-info/WHEEL
kripweb-0.0.4.dist-info/top_level.txt
kripweb-0.0.4.dist-info/RECORD
